cs/xml.py
cs.xml-20220606.dist-info/METADATA
cs.xml-20220606.dist-info/WHEEL
cs.xml-20220606.dist-info/top_level.txt
cs.xml-20220606.dist-info/RECORD
